{
  "id": "micro-econ-07-judge",
  "title": "微观经济学07-判断",
  "description": "完全竞争市场判断题测验",
  "questions": [
    {
      "id": 1,
      "question": "完全竞争厂商面对的需求曲线由市场价格所决定，故其完全缺乏弹性。",
      "options": ["正确", "错误"],
      "answer": 1,
      "isMultiple": false,
      "rationale": "刚好相反！其需求曲线是一条水平线，意味着具有\"完全弹性\"。只要你提价一分钱，所有顾客都会跑去买别人的。"
    },
    {
      "id": 2,
      "question": "在完全竞争行业中，企业的需求曲线是水平的，所以企业的 $MC$ 曲线也是水平的。",
      "options": ["正确", "错误"],
      "answer": 1,
      "isMultiple": false,
      "rationale": "需求线水平代表价格不变，但 $MC$ 线是由生产技术决定的，受边际报酬递减规律影响，它通常呈 U 型，先降后升。"
    },
    {
      "id": 3,
      "question": "如果一个企业的平均销售收入低于平均成本，则该企业应当停产。",
      "options": ["正确", "错误"],
      "answer": 1,
      "isMultiple": false,
      "rationale": "不一定。只要收入能覆盖\"平均可变成本\"（$AVC$），哪怕整体亏损，继续开工也能帮老板分摊一点固定成本（如租金），比直接关门亏得少。"
    },
    {
      "id": 4,
      "question": "在长期中，完全竞争厂商利润为零使厂商倾向于退出该行业。",
      "options": ["正确", "错误"],
      "answer": 1,
      "isMultiple": false,
      "rationale": "这里的零利润是\"经济利润\"。它已经扣除了老板干别行能赚到的钱。既然干这行能拿到社会平均工资，老板通常会选择留下。"
    },
    {
      "id": 5,
      "question": "在长期中，完全竞争市场的价格等于最低的长期平均成本。",
      "options": ["正确", "错误"],
      "answer": 0,
      "isMultiple": false,
      "rationale": "因为自由进出，有赚头大家就进，亏本大家就走，最后价格一定会被逼到 $LAC$ 的最低谷，实现资源配置的最佳效率。"
    },
    {
      "id": 6,
      "question": "在长期中，完全竞争市场中的厂商一般都拥有相同的成本曲线。",
      "options": ["正确", "错误"],
      "answer": 0,
      "isMultiple": false,
      "rationale": "长期内技术是公开流动的，要素价格也透明，大家都趋向于采用最成熟、最高效的生产配方，因此成本结构会逐渐统一。"
    },
    {
      "id": 7,
      "question": "在完全竞争的行业中，一个代表性企业的需求曲线与平均成本曲线相切，说明它处于长期均衡的位置。",
      "options": ["正确", "错误"],
      "answer": 0,
      "isMultiple": false,
      "rationale": "相切意味着 $P=AC$。没有诱人的超额利润让外行进，也没亏损让内行逃，市场达到了稳定的天平状态。"
    },
    {
      "id": 8,
      "question": "完全竞争市场的产品同质假定意味着厂商生产的产品中，商标、专利、品牌等的差异是不存在的。",
      "options": ["正确", "错误"],
      "answer": 0,
      "isMultiple": false,
      "rationale": "\"同质\"意味着产品完全标准化。消费者分不清是谁产的，只认型号和价格。"
    },
    {
      "id": 9,
      "question": "在长期中，如果一个行业的成本是不变的，那么市场需求的变化将完全反映在产量的调整上。",
      "options": ["正确", "错误"],
      "answer": 0,
      "isMultiple": false,
      "rationale": "既然成本不变，价格最终总会回到原点。需求增加了，价格短升后会引来更多厂商，直到产量拉升到新高，而价格维持原样。"
    },
    {
      "id": 10,
      "question": "在一个完全竞争行业中，没有一个企业能对物品的市场价格有任何重要的影响。",
      "options": ["正确", "错误"],
      "answer": 0,
      "isMultiple": false,
      "rationale": "典型的\"价格接受者\"描述。每个人都太微不足道，你的任何举动都翻不起市场的浪花。"
    },
    {
      "id": 11,
      "question": "在一个完全竞争行业中，对于进入该行业不存在限制。",
      "options": ["正确", "错误"],
      "answer": 0,
      "isMultiple": false,
      "rationale": "进出自由是完全竞争的基石。没有许可证、没有高技术门槛，资源可以随时流向最赚钱的地方。"
    },
    {
      "id": 12,
      "question": "一个完全竞争行业的企业所面临的需求曲线是完全无弹性的，需求曲线是一条垂线。",
      "options": ["正确", "错误"],
      "answer": 1,
      "isMultiple": false,
      "rationale": "垂线意味着无论价格多高你都得买（完全无弹性），这通常出现在救命药等行业。完全竞争厂商面对的是水平的需求曲线（完全弹性）。"
    },
    {
      "id": 13,
      "question": "完全竞争企业的目标是收益最大化。",
      "options": ["正确", "错误"],
      "answer": 1,
      "isMultiple": false,
      "rationale": "企业的目标永远是\"利润最大化\"。如果你卖得极多（收益大）但成本更高（亏损），那这种经营是失败的。"
    },
    {
      "id": 14,
      "question": "完全竞争行业 $AR$ 曲线和 $MR$ 曲线与需求曲线是相同的。",
      "options": ["正确", "错误"],
      "answer": 0,
      "isMultiple": false,
      "rationale": "因为价格恒定，卖每一件赚的钱（$MR$）和平均每件赚的钱（$AR$）都等于市场价，在图表上它们完美重合。"
    },
    {
      "id": 15,
      "question": "如果 $MR > MC$，企业就可以通过减少其产量来增加利润。",
      "options": ["正确", "错误"],
      "answer": 1,
      "isMultiple": false,
      "rationale": "既然多卖一件赚的（$MR$）比花的多（$MC$），那就应该增加产量去捞那部分还没赚到的利润。"
    },
    {
      "id": 16,
      "question": "在长期中，完全竞争的企业可能有经济亏损，但在短期中不会。",
      "options": ["正确", "错误"],
      "answer": 1,
      "isMultiple": false,
      "rationale": "逻辑反了。短期可能亏（来不及关门），但长期如果一直亏，厂商一定会卷铺盖走人，所以长期不可能维持亏损状态。"
    },
    {
      "id": 17,
      "question": "如果企业的经济利润为零，就实现了收支相抵。",
      "options": ["正确", "错误"],
      "answer": 0,
      "isMultiple": false,
      "rationale": "零利润点也叫盈亏平衡点（Breakeven Point），意味着所有经营成本都被填平了。"
    },
    {
      "id": 18,
      "question": "如果价格低于 $AVC$，企业就会停止生产。",
      "options": ["正确", "错误"],
      "answer": 0,
      "isMultiple": false,
      "rationale": "这是\"停产红线\"。连开工的变动成本（水电人工）都赚不回来，每多干一天都是在自掏腰包贴钱，必须停业。"
    },
    {
      "id": 19,
      "question": "在 $P > AVC$ 时，完全竞争企业的供给曲线和 $MR$ 曲线相同。",
      "options": ["正确", "错误"],
      "answer": 1,
      "isMultiple": false,
      "rationale": "企业的供给曲线是其边际成本（$MC$）曲线，而 $MR$ 曲线是水平的价格线，两者虽然在均衡点相交，但不是同一条线。"
    },
    {
      "id": 20,
      "question": "所有完全竞争的企业都可以在短期均衡时实现利润最大化。",
      "options": ["正确", "错误"],
      "answer": 0,
      "isMultiple": false,
      "rationale": "只要按照 $P=MC$ 来生产，企业在当前约束下就已经做到了\"最好\"（虽然这个最好有时也可能是亏损最小）。"
    },
    {
      "id": 21,
      "question": "在完全竞争市场可以把每个企业的供给曲线水平相加而得出行业短期供给曲线。",
      "options": ["正确", "错误"],
      "answer": 0,
      "isMultiple": false,
      "rationale": "行业的总供给就是所有小老板供应量的总和，这在几何上表现为横向加总。"
    },
    {
      "id": 22,
      "question": "在长期均衡时，完全竞争行业中的每个企业的经济利润为零。",
      "options": ["正确", "错误"],
      "answer": 0,
      "isMultiple": false,
      "rationale": "这是竞争的必然结果。只要有利润，新人就进，供过于求导致降价，直到利润被抹平。"
    },
    {
      "id": 23,
      "question": "新企业进入一个完全竞争行业会提高价格并增加每个企业的利润。",
      "options": ["正确", "错误"],
      "answer": 1,
      "isMultiple": false,
      "rationale": "新人进场会增加总供给，导致价格下跌，从而摊薄老商户的利润。"
    },
    {
      "id": 24,
      "question": "在长期均衡时，完全竞争行业中的每个企业都选择了与最低 $LAC$ 相一致的工厂规模。",
      "options": ["正确", "错误"],
      "answer": 0,
      "isMultiple": false,
      "rationale": "为了活下去，厂商必须把成本压到极致。长期均衡点强制要求厂商必须在最高效、最省钱的规模（$LAC$ 最低点）上运作。"
    }
  ]
}
